signapse/__init__.py
signapse/build_opt.py
signapse/compute.py
signapse/constants.py
signapse/create.py
signapse/create_model.py
signapse/heatmaps.py
signapse/lang_utils.py
signapse/models_utils.py
signapse/mp_utils.py
signapse/poses.py
signapse/preprocessing.py
signapse/sam2.py
signapse-1.1.6.dist-info/METADATA
signapse-1.1.6.dist-info/WHEEL
signapse-1.1.6.dist-info/top_level.txt
signapse-1.1.6.dist-info/RECORD
