Metadata-Version: 2.1
Name: signapse
Version: 1.1.6
Summary: Signapse_synthetic_signer
Home-page: https://github.com/signapse/signapse
Author: Basheer Alwaely
Author-email: basheer@signapse.ai
Classifier: Development Status :: 1 - Planning
Classifier: Intended Audience :: Developers
Classifier: License :: OSI Approved :: MIT License
Classifier: Programming Language :: Python :: 3
Classifier: Topic :: Software Development :: Libraries :: Python Modules
Requires-Python: >3.7
